hj_reachability/__init__.py
hj_reachability/artificial_dissipation.py
hj_reachability/boundary_conditions.py
hj_reachability/boundary_conditions_test.py
hj_reachability/dynamics.py
hj_reachability/grid.py
hj_reachability/grid_test.py
hj_reachability/sets.py
hj_reachability/sets_test.py
hj_reachability/solver.py
hj_reachability/solver_test.py
hj_reachability/time_integration.py
hj_reachability/utils.py
hj_reachability/utils_test.py
hj_reachability/finite_differences/__init__.py
hj_reachability/finite_differences/upwind_first.py
hj_reachability/finite_differences/upwind_first_test.py
hj_reachability/systems/__init__.py
hj_reachability/systems/air3d.py
hj_reachability-0.7.0.dist-info/LICENSE
hj_reachability-0.7.0.dist-info/METADATA
hj_reachability-0.7.0.dist-info/WHEEL
hj_reachability-0.7.0.dist-info/top_level.txt
hj_reachability-0.7.0.dist-info/RECORD
