Metadata-Version: 2.1
Name: hj_reachability
Version: 0.7.0
Summary: Hamilton-Jacobi reachability analysis in JAX.
Home-page: https://github.com/StanfordASL/hj_reachability
Author: Ed Schmerling
Author-email: ednerd@gmail.com
License: MIT
Requires-Python: ~=3.8
License-File: LICENSE
Requires-Dist: flax >=0.6.6
Requires-Dist: jax >=0.4.25
Requires-Dist: numpy >=1.22
